odoo/addons/shopinvader_quotation_payment/README.rst
odoo/addons/shopinvader_quotation_payment/__init__.py
odoo/addons/shopinvader_quotation_payment/__manifest__.py
odoo/addons/shopinvader_quotation_payment/readme/CONTRIBUTORS.rst
odoo/addons/shopinvader_quotation_payment/readme/CREDITS.rst
odoo/addons/shopinvader_quotation_payment/readme/DESCRIPTION.rst
odoo/addons/shopinvader_quotation_payment/services/__init__.py
odoo/addons/shopinvader_quotation_payment/services/cart.py
odoo/addons/shopinvader_quotation_payment/services/invader_payment_service.py
odoo/addons/shopinvader_quotation_payment/services/quotation.py
odoo/addons/shopinvader_quotation_payment/static/description/index.html
odoo12_addon_shopinvader_quotation_payment-12.0.2.0.0.dist-info/METADATA
odoo12_addon_shopinvader_quotation_payment-12.0.2.0.0.dist-info/WHEEL
odoo12_addon_shopinvader_quotation_payment-12.0.2.0.0.dist-info/top_level.txt
odoo12_addon_shopinvader_quotation_payment-12.0.2.0.0.dist-info/RECORD
