Metadata-Version: 2.1
Name: odoo12-addon-shopinvader-quotation-payment
Version: 12.0.2.0.0
Summary: Shopinvader Quotation Payment
Home-page: https://akretion.com
Author: Akretion
License: AGPL-3
Platform: UNKNOWN
Classifier: Programming Language :: Python
Classifier: Framework :: Odoo
Classifier: License :: OSI Approved :: GNU Affero General Public License v3
Requires-Python: >=3.5
Requires-Dist: odoo12-addon-shopinvader-payment
Requires-Dist: odoo12-addon-shopinvader-quotation
Requires-Dist: odoo (<12.1dev,>=12.0a)
